Metadata-Version: 2.1
Name: SWPQueue
Version: 1.0.0
Summary: 基于文件读写实现的简单消息队列
Home-page: https://gitee.com/w-8/SimpleQueue
Author: bili:凿寂
Author-email: mdzzdyxc@163.com
License: MIT
Platform: UNKNOWN
Classifier: Programming Language :: Python :: 3
Classifier: License :: OSI Approved :: MIT License
Classifier: Operating System :: OS Independent
License-File: LICENSE
